{
  "station": "A363",
  "year": 2010,
  "months": [
    {
      "m": 1,
      "p": 76.0,
      "tmean": 26.3
    },
    {
      "m": 2,
      "p": 84.2,
      "tmean": 27.7
    },
    {
      "m": 3,
      "p": 187.0,
      "tmean": 26.9
    },
    {
      "m": 4,
      "p": 100.4,
      "tmean": 26.6
    },
    {
      "m": 5,
      "p": 30.8,
      "tmean": 27.5
    },
    {
      "m": 6,
      "p": 13.0,
      "tmean": 26.6
    },
    {
      "m": 7,
      "p": 2.2,
      "tmean": 27.2
    },
    {
      "m": 8,
      "p": 0.0,
      "tmean": 27.8
    },
    {
      "m": 9,
      "p": 0.0,
      "tmean": 29.1
    },
    {
      "m": 10,
      "p": 147.0,
      "tmean": 29.1
    },
    {
      "m": 11,
      "p": 10.6,
      "tmean": 28.6
    },
    {
      "m": 12,
      "p": 106.6,
      "tmean": 26.5
    }
  ],
  "annual": {
    "p_total": 757.8,
    "p_month_mean": 63.1,
    "p_month_min": 0.0,
    "p_month_max": 187.0,
    "tmean": 27.5,
    "tmin": 26.3,
    "tmax": 29.1
  }
}