{
  "station": "A514",
  "year": 2024,
  "months": [
    {
      "m": 1,
      "tmean": 22.37,
      "p": 274.0
    },
    {
      "m": 2,
      "tmean": 22.64,
      "p": 141.2
    },
    {
      "m": 3,
      "tmean": 22.9,
      "p": 188.0
    },
    {
      "m": 4,
      "tmean": 21.57,
      "p": 3.0
    },
    {
      "m": 5,
      "tmean": 19.94,
      "p": 27.0
    },
    {
      "m": 6,
      "tmean": 17.21,
      "p": 4.0
    },
    {
      "m": 7,
      "tmean": 17.21,
      "p": 1.6
    },
    {
      "m": 8,
      "tmean": 17.97,
      "p": 0.8
    },
    {
      "m": 9,
      "tmean": 21.95,
      "p": 33.0
    },
    {
      "m": 10,
      "tmean": 21.42,
      "p": 193.8
    },
    {
      "m": 11,
      "tmean": 21.2,
      "p": 328.6
    },
    {
      "m": 12,
      "tmean": 22.1,
      "p": 234.2
    }
  ],
  "annual": {
    "tmin": 5.2,
    "tmean": 20.7,
    "tmax": 33.8,
    "p_total": 1429.2,
    "p_month_min": 0.8,
    "p_month_mean": 119.1,
    "p_month_max": 328.6,
    "coverage": 1.0
  }
}