{
  "station": "A125",
  "year": 2014,
  "months": [
    {
      "m": 1,
      "p": 228.0,
      "tmean": 25.6
    },
    {
      "m": 2,
      "p": 330.6,
      "tmean": 24.9
    },
    {
      "m": 3,
      "p": 498.2,
      "tmean": 25.4
    },
    {
      "m": 4,
      "p": 348.4,
      "tmean": 25.4
    },
    {
      "m": 5,
      "p": 326.4,
      "tmean": 25.5
    },
    {
      "m": 6,
      "p": 174.0,
      "tmean": 25.7
    },
    {
      "m": 7,
      "p": 137.2,
      "tmean": 25.2
    },
    {
      "m": 8,
      "p": 64.4,
      "tmean": 25.9
    },
    {
      "m": 9,
      "p": 75.6,
      "tmean": 26.8
    },
    {
      "m": 10,
      "p": 167.6,
      "tmean": 26.0
    },
    {
      "m": 11,
      "p": 162.6,
      "tmean": 26.1
    },
    {
      "m": 12,
      "p": 182.4,
      "tmean": 26.3
    }
  ],
  "annual": {
    "p_total": 2695.4,
    "p_month_mean": 224.6,
    "p_month_min": 64.4,
    "p_month_max": 498.2,
    "tmean": 25.7,
    "tmin": 24.9,
    "tmax": 26.8
  }
}