{
  "station": "A203",
  "year": 2005,
  "months": [
    {
      "m": 1,
      "p": 31.2,
      "tmean": 27.6
    },
    {
      "m": 2,
      "p": 226.0,
      "tmean": 27.3
    },
    {
      "m": 3,
      "p": 339.0,
      "tmean": 26.4
    },
    {
      "m": 4,
      "p": 350.2,
      "tmean": 26.5
    },
    {
      "m": 5,
      "p": 136.8,
      "tmean": 27.0
    },
    {
      "m": 6,
      "p": 100.4,
      "tmean": 28.8
    },
    {
      "m": 7,
      "p": 82.0,
      "tmean": 28.8
    },
    {
      "m": 8,
      "p": 9.8,
      "tmean": 27.9
    },
    {
      "m": 9,
      "p": 0.0,
      "tmean": 27.1
    },
    {
      "m": 10,
      "p": 0.2,
      "tmean": 27.5
    },
    {
      "m": 11,
      "p": 4.0,
      "tmean": 28.0
    },
    {
      "m": 12,
      "p": 78.0,
      "tmean": 27.1
    }
  ],
  "annual": {
    "p_total": 1357.6,
    "p_month_mean": 113.1,
    "p_month_min": 0.0,
    "p_month_max": 350.2,
    "tmean": 27.5,
    "tmin": 26.4,
    "tmax": 28.8
  }
}