{
  "station": "A544",
  "year": 2009,
  "months": [
    {
      "m": 1,
      "p": 305.8,
      "tmean": 22.5
    },
    {
      "m": 2,
      "p": 83.2,
      "tmean": 23.7
    },
    {
      "m": 3,
      "p": 162.8,
      "tmean": 24.5
    },
    {
      "m": 4,
      "p": 181.2,
      "tmean": 21.6
    },
    {
      "m": 5,
      "p": 45.6,
      "tmean": 20.3
    },
    {
      "m": 6,
      "p": 28.0,
      "tmean": 19.9
    },
    {
      "m": 7,
      "p": 0.0,
      "tmean": 21.2
    },
    {
      "m": 8,
      "p": 37.4,
      "tmean": 21.6
    },
    {
      "m": 9,
      "p": 11.6,
      "tmean": 24.3
    },
    {
      "m": 10,
      "p": 174.2,
      "tmean": 23.3
    },
    {
      "m": 11,
      "p": 87.0,
      "tmean": 23.6
    },
    {
      "m": 12,
      "p": 245.0,
      "tmean": 22.2
    }
  ],
  "annual": {
    "p_total": 1361.8,
    "p_month_mean": 113.5,
    "p_month_min": 0.0,
    "p_month_max": 305.8,
    "tmean": 22.4,
    "tmin": 19.9,
    "tmax": 24.5
  }
}