{
  "station": "A829",
  "year": 2017,
  "months": [
    {
      "m": 1,
      "p": 219.2,
      "tmean": 18.1
    },
    {
      "m": 2,
      "p": 69.0,
      "tmean": 19.1
    },
    {
      "m": 3,
      "p": 101.2,
      "tmean": 16.0
    },
    {
      "m": 4,
      "p": 140.2,
      "tmean": 13.5
    },
    {
      "m": 5,
      "p": 174.4,
      "tmean": 12.6
    },
    {
      "m": 6,
      "p": 116.8,
      "tmean": 10.9
    },
    {
      "m": 7,
      "p": 6.8,
      "tmean": 10.8
    },
    {
      "m": 8,
      "p": 93.2,
      "tmean": 11.6
    },
    {
      "m": 9,
      "p": 133.4,
      "tmean": 15.8
    },
    {
      "m": 10,
      "p": 195.0,
      "tmean": 13.8
    },
    {
      "m": 11,
      "p": 153.8,
      "tmean": 13.9
    },
    {
      "m": 12,
      "p": 82.6,
      "tmean": 16.8
    }
  ],
  "annual": {
    "p_total": 1485.6,
    "p_month_mean": 123.8,
    "p_month_min": 6.8,
    "p_month_max": 219.2,
    "tmean": 14.4,
    "tmin": 10.8,
    "tmax": 19.1
  }
}