{
  "station": "A502",
  "year": 2017,
  "months": [
    {
      "m": 1,
      "p": 104.2,
      "tmean": 21.5
    },
    {
      "m": 2,
      "p": 257.0,
      "tmean": 20.6
    },
    {
      "m": 3,
      "p": 100.2,
      "tmean": 19.8
    },
    {
      "m": 4,
      "p": 55.4,
      "tmean": 18.3
    },
    {
      "m": 5,
      "p": 92.2,
      "tmean": 16.4
    },
    {
      "m": 6,
      "p": 31.0,
      "tmean": 16.2
    },
    {
      "m": 7,
      "p": 9.8,
      "tmean": 13.6
    },
    {
      "m": 8,
      "p": 0.8,
      "tmean": 15.7
    },
    {
      "m": 9,
      "p": 11.4,
      "tmean": 17.7
    },
    {
      "m": 10,
      "p": 101.8,
      "tmean": 20.0
    },
    {
      "m": 11,
      "p": 158.8,
      "tmean": 18.7
    },
    {
      "m": 12,
      "p": 308.4,
      "tmean": 20.2
    }
  ],
  "annual": {
    "p_total": 1231.0,
    "p_month_mean": 102.6,
    "p_month_min": 0.8,
    "p_month_max": 308.4,
    "tmean": 18.2,
    "tmin": 13.6,
    "tmax": 21.5
  }
}