{
  "station": "A630",
  "year": 2024,
  "months": [
    {
      "m": 1,
      "tmean": 23.25,
      "p": 274.6
    },
    {
      "m": 2,
      "tmean": 23.48,
      "p": 127.2
    },
    {
      "m": 3,
      "tmean": 23.27,
      "p": 177.2
    },
    {
      "m": 4,
      "tmean": 21.43,
      "p": 16.6
    },
    {
      "m": 5,
      "tmean": 20.61,
      "p": 35.2
    },
    {
      "m": 6,
      "tmean": 18.05,
      "p": 1.6
    },
    {
      "m": 7,
      "tmean": 17.72,
      "p": 26.2
    },
    {
      "m": 8,
      "tmean": 17.68,
      "p": 40.4
    },
    {
      "m": 9,
      "tmean": 20.69,
      "p": 15.2
    },
    {
      "m": 10,
      "tmean": 21.69,
      "p": 109.2
    },
    {
      "m": 11,
      "tmean": 21.51,
      "p": 204.4
    },
    {
      "m": 12,
      "tmean": 23.63,
      "p": 78.2
    }
  ],
  "annual": {
    "tmin": 7.6,
    "tmean": 20.91,
    "tmax": 33.1,
    "p_total": 1106.0,
    "p_month_min": 1.6,
    "p_month_mean": 92.2,
    "p_month_max": 274.6,
    "coverage": 0.945
  }
}