{
  "station": "A858",
  "year": 2011,
  "months": [
    {
      "m": 1,
      "p": 114.0,
      "tmean": 22.1
    },
    {
      "m": 2,
      "p": 244.8,
      "tmean": 21.3
    },
    {
      "m": 3,
      "p": 207.0,
      "tmean": 20.4
    },
    {
      "m": 4,
      "p": 145.6,
      "tmean": 18.8
    },
    {
      "m": 5,
      "p": 67.0,
      "tmean": 15.0
    },
    {
      "m": 6,
      "p": 367.6,
      "tmean": 13.0
    },
    {
      "m": 7,
      "p": 231.4,
      "tmean": 14.6
    },
    {
      "m": 8,
      "p": 207.6,
      "tmean": 14.9
    },
    {
      "m": 9,
      "p": 175.2,
      "tmean": 16.4
    },
    {
      "m": 10,
      "p": 256.2,
      "tmean": 18.6
    },
    {
      "m": 11,
      "p": 100.4,
      "tmean": 19.7
    },
    {
      "m": 12,
      "p": 87.6,
      "tmean": 21.1
    }
  ],
  "annual": {
    "p_total": 2204.4,
    "p_month_mean": 183.7,
    "p_month_min": 67.0,
    "p_month_max": 367.6,
    "tmean": 18.0,
    "tmin": 13.0,
    "tmax": 22.1
  }
}