{
  "station": "A410",
  "year": 2003,
  "months": [
    {
      "m": 1,
      "p": 44.0,
      "tmean": 25.9
    },
    {
      "m": 2,
      "p": 122.4,
      "tmean": 25.3
    },
    {
      "m": 3,
      "p": 177.6,
      "tmean": 25.2
    },
    {
      "m": 4,
      "p": 162.0,
      "tmean": 24.8
    },
    {
      "m": 5,
      "p": 203.0,
      "tmean": 23.6
    },
    {
      "m": 6,
      "p": 168.2,
      "tmean": 22.2
    },
    {
      "m": 7,
      "p": 151.0,
      "tmean": 21.4
    },
    {
      "m": 8,
      "p": 200.6,
      "tmean": 21.7
    },
    {
      "m": 9,
      "p": 105.0,
      "tmean": 22.2
    },
    {
      "m": 10,
      "p": 55.0,
      "tmean": 23.1
    },
    {
      "m": 11,
      "p": 45.0,
      "tmean": 24.2
    },
    {
      "m": 12,
      "p": 101.2,
      "tmean": 25.2
    }
  ],
  "annual": {
    "p_total": 1535.0,
    "p_month_mean": 127.9,
    "p_month_min": 44.0,
    "p_month_max": 203.0,
    "tmean": 23.7,
    "tmin": 21.4,
    "tmax": 25.9
  }
}