{
  "station": "A223",
  "year": 2015,
  "months": [
    {
      "m": 1,
      "p": 152.6,
      "tmean": 26.3
    },
    {
      "m": 2,
      "p": 252.6,
      "tmean": 25.3
    },
    {
      "m": 3,
      "p": 240.6,
      "tmean": 25.2
    },
    {
      "m": 4,
      "p": 142.8,
      "tmean": 26.0
    },
    {
      "m": 5,
      "p": 40.8,
      "tmean": 26.3
    },
    {
      "m": 6,
      "p": 0.0,
      "tmean": 25.4
    },
    {
      "m": 7,
      "p": 0.0,
      "tmean": 25.9
    },
    {
      "m": 8,
      "p": 0.0,
      "tmean": 25.9
    },
    {
      "m": 9,
      "p": 5.0,
      "tmean": 28.3
    },
    {
      "m": 10,
      "p": 17.4,
      "tmean": 29.6
    },
    {
      "m": 11,
      "p": 110.6,
      "tmean": 28.1
    },
    {
      "m": 12,
      "p": 44.8,
      "tmean": 28.5
    }
  ],
  "annual": {
    "p_total": 1007.2,
    "p_month_mean": 83.9,
    "p_month_min": 0.0,
    "p_month_max": 252.6,
    "tmean": 26.7,
    "tmin": 25.2,
    "tmax": 29.6
  }
}