{
  "station": "A712",
  "year": 2010,
  "months": [
    {
      "m": 1,
      "p": 470.0,
      "tmean": 25.6
    },
    {
      "m": 2,
      "p": 269.2,
      "tmean": 26.8
    },
    {
      "m": 3,
      "p": 165.8,
      "tmean": 24.7
    },
    {
      "m": 4,
      "p": 252.6,
      "tmean": 22.1
    },
    {
      "m": 5,
      "p": 143.6,
      "tmean": 19.9
    },
    {
      "m": 6,
      "p": 84.6,
      "tmean": 17.9
    },
    {
      "m": 7,
      "p": 231.6,
      "tmean": 18.7
    },
    {
      "m": 8,
      "p": 48.0,
      "tmean": 17.6
    },
    {
      "m": 9,
      "p": 79.0,
      "tmean": 19.6
    },
    {
      "m": 10,
      "p": 95.6,
      "tmean": 19.8
    },
    {
      "m": 11,
      "p": 109.4,
      "tmean": 22.0
    },
    {
      "m": 12,
      "p": 468.6,
      "tmean": 23.8
    }
  ],
  "annual": {
    "p_total": 2418.0,
    "p_month_mean": 201.5,
    "p_month_min": 48.0,
    "p_month_max": 470.0,
    "tmean": 21.5,
    "tmin": 17.6,
    "tmax": 26.8
  }
}