{
  "station": "A702",
  "year": 2005,
  "months": [
    {
      "m": 1,
      "p": 237.2,
      "tmean": 24.6
    },
    {
      "m": 2,
      "p": 142.2,
      "tmean": 25.8
    },
    {
      "m": 3,
      "p": 90.6,
      "tmean": 25.4
    },
    {
      "m": 4,
      "p": 64.4,
      "tmean": 24.3
    },
    {
      "m": 5,
      "p": 114.8,
      "tmean": 22.5
    },
    {
      "m": 6,
      "p": 123.4,
      "tmean": 22.1
    },
    {
      "m": 7,
      "p": 20.2,
      "tmean": 19.0
    },
    {
      "m": 8,
      "p": 7.6,
      "tmean": 23.0
    },
    {
      "m": 9,
      "p": 62.4,
      "tmean": 21.0
    },
    {
      "m": 10,
      "p": 140.0,
      "tmean": 24.8
    },
    {
      "m": 11,
      "p": 210.2,
      "tmean": 24.6
    },
    {
      "m": 12,
      "p": 168.6,
      "tmean": 25.0
    }
  ],
  "annual": {
    "p_total": 1381.6,
    "p_month_mean": 115.1,
    "p_month_min": 7.6,
    "p_month_max": 237.2,
    "tmean": 23.5,
    "tmin": 19.0,
    "tmax": 25.8
  }
}