{
  "station": "A436",
  "year": 2015,
  "months": [
    {
      "m": 1,
      "p": 4.6,
      "tmean": 26.7
    },
    {
      "m": 2,
      "p": 79.6,
      "tmean": 26.8
    },
    {
      "m": 3,
      "p": 24.2,
      "tmean": 27.6
    },
    {
      "m": 4,
      "p": 57.6,
      "tmean": 27.2
    },
    {
      "m": 5,
      "p": 58.4,
      "tmean": 24.7
    },
    {
      "m": 6,
      "p": 75.0,
      "tmean": 22.9
    },
    {
      "m": 7,
      "p": 32.4,
      "tmean": 22.6
    },
    {
      "m": 8,
      "p": 27.0,
      "tmean": 23.0
    },
    {
      "m": 9,
      "p": 5.2,
      "tmean": 25.8
    },
    {
      "m": 10,
      "p": 12.8,
      "tmean": 26.6
    },
    {
      "m": 11,
      "p": 1.6,
      "tmean": 28.9
    },
    {
      "m": 12,
      "p": 1.0,
      "tmean": 28.6
    }
  ],
  "annual": {
    "p_total": 379.4,
    "p_month_mean": 31.6,
    "p_month_min": 1.0,
    "p_month_max": 79.6,
    "tmean": 25.9,
    "tmin": 22.6,
    "tmax": 28.9
  }
}