{
  "station": "A820",
  "year": 2015,
  "months": [
    {
      "m": 1,
      "p": 4.2,
      "tmean": 29.8
    },
    {
      "m": 2,
      "p": 58.2,
      "tmean": 27.7
    },
    {
      "m": 3,
      "p": 75.2,
      "tmean": 24.3
    },
    {
      "m": 4,
      "p": 157.4,
      "tmean": 22.0
    },
    {
      "m": 5,
      "p": 221.6,
      "tmean": 18.9
    },
    {
      "m": 6,
      "p": 91.6,
      "tmean": 18.7
    },
    {
      "m": 7,
      "p": 338.6,
      "tmean": 17.1
    },
    {
      "m": 8,
      "p": 15.0,
      "tmean": 21.8
    },
    {
      "m": 9,
      "p": 0.0,
      "tmean": 23.2
    },
    {
      "m": 10,
      "p": 126.6,
      "tmean": 24.3
    },
    {
      "m": 11,
      "p": 374.6,
      "tmean": 22.9
    },
    {
      "m": 12,
      "p": 424.8,
      "tmean": 23.7
    }
  ],
  "annual": {
    "p_total": 1887.8,
    "p_month_mean": 157.3,
    "p_month_min": 0.0,
    "p_month_max": 424.8,
    "tmean": 22.9,
    "tmin": 17.1,
    "tmax": 29.8
  }
}