{
  "station": "A405",
  "year": 2010,
  "months": [
    {
      "m": 1,
      "p": 21.6,
      "tmean": 27.4
    },
    {
      "m": 2,
      "p": 36.4,
      "tmean": 27.6
    },
    {
      "m": 3,
      "p": 181.2,
      "tmean": 27.2
    },
    {
      "m": 4,
      "p": 255.6,
      "tmean": 25.6
    },
    {
      "m": 5,
      "p": 62.4,
      "tmean": 25.6
    },
    {
      "m": 6,
      "p": 25.8,
      "tmean": 23.4
    },
    {
      "m": 7,
      "p": 0.4,
      "tmean": 25.0
    },
    {
      "m": 8,
      "p": 0.0,
      "tmean": 24.9
    },
    {
      "m": 9,
      "p": null,
      "tmean": null
    },
    {
      "m": 10,
      "p": 0.0,
      "tmean": 25.4
    },
    {
      "m": 11,
      "p": 461.6,
      "tmean": 25.0
    },
    {
      "m": 12,
      "p": 20.4,
      "tmean": 26.2
    }
  ],
  "annual": {
    "p_total": 1065.4,
    "p_month_mean": 96.9,
    "p_month_min": 0.0,
    "p_month_max": 461.6,
    "tmean": 25.8,
    "tmin": 23.4,
    "tmax": 27.6
  }
}