{
  "station": "A746",
  "year": 2013,
  "months": [
    {
      "m": 1,
      "p": 12.0,
      "tmean": 20.0
    },
    {
      "m": 2,
      "p": 58.4,
      "tmean": 21.9
    },
    {
      "m": 3,
      "p": 170.2,
      "tmean": 19.7
    },
    {
      "m": 4,
      "p": 58.4,
      "tmean": 17.6
    },
    {
      "m": 5,
      "p": 84.8,
      "tmean": 15.9
    },
    {
      "m": 6,
      "p": 220.8,
      "tmean": 15.6
    },
    {
      "m": 7,
      "p": 78.2,
      "tmean": 13.0
    },
    {
      "m": 8,
      "p": 32.0,
      "tmean": 13.4
    },
    {
      "m": 9,
      "p": 72.4,
      "tmean": 15.6
    },
    {
      "m": 10,
      "p": 70.4,
      "tmean": 17.3
    },
    {
      "m": 11,
      "p": 247.4,
      "tmean": 18.9
    },
    {
      "m": 12,
      "p": 191.8,
      "tmean": 21.1
    }
  ],
  "annual": {
    "p_total": 1296.8,
    "p_month_mean": 108.1,
    "p_month_min": 12.0,
    "p_month_max": 247.4,
    "tmean": 17.5,
    "tmin": 13.0,
    "tmax": 21.9
  }
}