{
  "station": "A419",
  "year": 2011,
  "months": [
    {
      "m": 1,
      "p": 66.4,
      "tmean": 25.5
    },
    {
      "m": 2,
      "p": 25.6,
      "tmean": 25.6
    },
    {
      "m": 3,
      "p": 149.8,
      "tmean": 26.3
    },
    {
      "m": 4,
      "p": 89.0,
      "tmean": 24.5
    },
    {
      "m": 5,
      "p": 82.4,
      "tmean": 23.2
    },
    {
      "m": 6,
      "p": 47.0,
      "tmean": 22.0
    },
    {
      "m": 7,
      "p": 56.0,
      "tmean": 21.0
    },
    {
      "m": 8,
      "p": 51.0,
      "tmean": 21.8
    },
    {
      "m": 9,
      "p": 23.6,
      "tmean": 22.0
    },
    {
      "m": 10,
      "p": 91.0,
      "tmean": 24.2
    },
    {
      "m": 11,
      "p": 26.8,
      "tmean": 24.9
    },
    {
      "m": 12,
      "p": 1.2,
      "tmean": 26.1
    }
  ],
  "annual": {
    "p_total": 709.8,
    "p_month_mean": 59.2,
    "p_month_min": 1.2,
    "p_month_max": 149.8,
    "tmean": 23.9,
    "tmin": 21.0,
    "tmax": 26.3
  }
}