{
  "station": "A925",
  "year": 2023,
  "months": [
    {
      "m": 1,
      "tmean": 25.78,
      "p": 30.2
    },
    {
      "m": 2,
      "tmean": null,
      "p": null
    },
    {
      "m": 3,
      "tmean": 27.01,
      "p": 3.6
    },
    {
      "m": 4,
      "tmean": 26.48,
      "p": 64.8
    },
    {
      "m": 5,
      "tmean": 26.76,
      "p": 34.4
    },
    {
      "m": 6,
      "tmean": 25.02,
      "p": 89.2
    },
    {
      "m": 7,
      "tmean": 24.26,
      "p": 15.4
    },
    {
      "m": 8,
      "tmean": 25.55,
      "p": 119.4
    },
    {
      "m": 9,
      "tmean": 26.58,
      "p": 54.2
    },
    {
      "m": 10,
      "tmean": 26.83,
      "p": 133.0
    },
    {
      "m": 11,
      "tmean": 26.83,
      "p": 192.4
    },
    {
      "m": 12,
      "tmean": 26.98,
      "p": 331.6
    }
  ],
  "annual": {
    "tmin": 17.5,
    "tmean": 26.1,
    "tmax": 36.5,
    "p_total": 1068.2,
    "p_month_min": 3.6,
    "p_month_mean": 89.0,
    "p_month_max": 331.6,
    "coverage": 0.705
  }
}