{
  "station": "A119",
  "year": 2018,
  "months": [
    {
      "m": 1,
      "p": 125.8,
      "tmean": 26.3
    },
    {
      "m": 2,
      "p": 264.4,
      "tmean": 26.8
    },
    {
      "m": 3,
      "p": 328.0,
      "tmean": 26.7
    },
    {
      "m": 4,
      "p": 284.6,
      "tmean": 26.3
    },
    {
      "m": 5,
      "p": 162.6,
      "tmean": 26.5
    },
    {
      "m": 6,
      "p": 121.4,
      "tmean": 27.0
    },
    {
      "m": 7,
      "p": 48.0,
      "tmean": 27.4
    },
    {
      "m": 8,
      "p": 99.0,
      "tmean": 27.7
    },
    {
      "m": 9,
      "p": 82.2,
      "tmean": 28.7
    },
    {
      "m": 10,
      "p": 89.4,
      "tmean": 29.3
    },
    {
      "m": 11,
      "p": 132.0,
      "tmean": 27.9
    },
    {
      "m": 12,
      "p": 381.4,
      "tmean": 26.0
    }
  ],
  "annual": {
    "p_total": 2118.8,
    "p_month_mean": 176.6,
    "p_month_min": 48.0,
    "p_month_max": 381.4,
    "tmean": 27.2,
    "tmin": 26.0,
    "tmax": 29.3
  }
}