{
  "station": "A612",
  "year": 2010,
  "months": [
    {
      "m": 1,
      "p": 1.0,
      "tmean": 28.0
    },
    {
      "m": 2,
      "p": 37.0,
      "tmean": 27.8
    },
    {
      "m": 3,
      "p": 357.4,
      "tmean": 26.9
    },
    {
      "m": 4,
      "p": 164.0,
      "tmean": 25.0
    },
    {
      "m": 5,
      "p": 124.8,
      "tmean": 23.3
    },
    {
      "m": 6,
      "p": 52.0,
      "tmean": 20.6
    },
    {
      "m": 7,
      "p": 117.8,
      "tmean": 21.5
    },
    {
      "m": 8,
      "p": 14.4,
      "tmean": 21.0
    },
    {
      "m": 9,
      "p": 28.4,
      "tmean": 22.8
    },
    {
      "m": 10,
      "p": 52.8,
      "tmean": 23.5
    },
    {
      "m": 11,
      "p": 268.0,
      "tmean": 24.4
    },
    {
      "m": 12,
      "p": 212.2,
      "tmean": 26.5
    }
  ],
  "annual": {
    "p_total": 1429.8,
    "p_month_mean": 119.1,
    "p_month_min": 1.0,
    "p_month_max": 357.4,
    "tmean": 24.3,
    "tmin": 20.6,
    "tmax": 28.0
  }
}