{
  "station": "A525",
  "year": 2016,
  "months": [
    {
      "m": 1,
      "p": 376.4,
      "tmean": 23.2
    },
    {
      "m": 2,
      "p": 208.8,
      "tmean": 23.8
    },
    {
      "m": 3,
      "p": 309.8,
      "tmean": 23.3
    },
    {
      "m": 4,
      "p": 14.8,
      "tmean": 23.1
    },
    {
      "m": 5,
      "p": 9.0,
      "tmean": 20.6
    },
    {
      "m": 6,
      "p": 115.2,
      "tmean": 18.5
    },
    {
      "m": 7,
      "p": 0.0,
      "tmean": 19.5
    },
    {
      "m": 8,
      "p": 29.6,
      "tmean": 21.0
    },
    {
      "m": 9,
      "p": 0.2,
      "tmean": 23.3
    },
    {
      "m": 10,
      "p": 107.0,
      "tmean": 23.6
    },
    {
      "m": 11,
      "p": 300.2,
      "tmean": 22.3
    },
    {
      "m": 12,
      "p": 323.8,
      "tmean": 23.3
    }
  ],
  "annual": {
    "p_total": 1794.8,
    "p_month_mean": 149.6,
    "p_month_min": 0.0,
    "p_month_max": 376.4,
    "tmean": 22.1,
    "tmin": 18.5,
    "tmax": 23.8
  }
}