{
  "station": "A531",
  "year": 2009,
  "months": [
    {
      "m": 1,
      "p": 344.0,
      "tmean": 18.7
    },
    {
      "m": 2,
      "p": 307.2,
      "tmean": 19.4
    },
    {
      "m": 3,
      "p": 148.6,
      "tmean": 19.2
    },
    {
      "m": 4,
      "p": 54.4,
      "tmean": 16.2
    },
    {
      "m": 5,
      "p": 100.4,
      "tmean": 14.4
    },
    {
      "m": 6,
      "p": 55.8,
      "tmean": 11.6
    },
    {
      "m": 7,
      "p": 69.6,
      "tmean": 14.0
    },
    {
      "m": 8,
      "p": 84.0,
      "tmean": 14.4
    },
    {
      "m": 9,
      "p": 144.0,
      "tmean": 17.1
    },
    {
      "m": 10,
      "p": 167.0,
      "tmean": 18.2
    },
    {
      "m": 11,
      "p": 250.2,
      "tmean": 19.9
    },
    {
      "m": 12,
      "p": 390.8,
      "tmean": 19.4
    }
  ],
  "annual": {
    "p_total": 2116.0,
    "p_month_mean": 176.3,
    "p_month_min": 54.4,
    "p_month_max": 390.8,
    "tmean": 16.9,
    "tmin": 11.6,
    "tmax": 19.9
  }
}