{
  "station": "A807",
  "year": 2014,
  "months": [
    {
      "m": 1,
      "p": 243.2,
      "tmean": 22.8
    },
    {
      "m": 2,
      "p": 113.6,
      "tmean": 22.6
    },
    {
      "m": 3,
      "p": 212.0,
      "tmean": 20.4
    },
    {
      "m": 4,
      "p": 75.8,
      "tmean": 18.2
    },
    {
      "m": 5,
      "p": 87.8,
      "tmean": 16.1
    },
    {
      "m": 6,
      "p": 200.6,
      "tmean": 15.6
    },
    {
      "m": 7,
      "p": 27.2,
      "tmean": 15.0
    },
    {
      "m": 8,
      "p": null,
      "tmean": null
    },
    {
      "m": 9,
      "p": null,
      "tmean": null
    },
    {
      "m": 10,
      "p": 21.0,
      "tmean": 20.3
    },
    {
      "m": 11,
      "p": 115.0,
      "tmean": 19.3
    },
    {
      "m": 12,
      "p": 150.4,
      "tmean": 21.0
    }
  ],
  "annual": {
    "p_total": 1246.6,
    "p_month_mean": 124.7,
    "p_month_min": 21.0,
    "p_month_max": 243.2,
    "tmean": 19.1,
    "tmin": 15.0,
    "tmax": 22.8
  }
}