{
  "station": "A845",
  "year": 2013,
  "months": [
    {
      "m": 1,
      "p": 277.0,
      "tmean": 12.6
    },
    {
      "m": 2,
      "p": 322.2,
      "tmean": 13.9
    },
    {
      "m": 3,
      "p": 370.2,
      "tmean": 11.8
    },
    {
      "m": 4,
      "p": 93.4,
      "tmean": 11.1
    },
    {
      "m": 5,
      "p": 92.0,
      "tmean": 10.0
    },
    {
      "m": 6,
      "p": 249.8,
      "tmean": 8.6
    },
    {
      "m": 7,
      "p": 121.6,
      "tmean": 7.8
    },
    {
      "m": 8,
      "p": 597.8,
      "tmean": 7.7
    },
    {
      "m": 9,
      "p": 340.2,
      "tmean": 9.4
    },
    {
      "m": 10,
      "p": 179.8,
      "tmean": 9.3
    },
    {
      "m": 11,
      "p": 234.8,
      "tmean": 11.6
    },
    {
      "m": 12,
      "p": 80.6,
      "tmean": 13.8
    }
  ],
  "annual": {
    "p_total": 2959.4,
    "p_month_mean": 246.6,
    "p_month_min": 80.6,
    "p_month_max": 597.8,
    "tmean": 10.6,
    "tmin": 7.7,
    "tmax": 13.9
  }
}