{
  "station": "A003",
  "year": 2024,
  "months": [
    {
      "m": 1,
      "tmean": 24.83,
      "p": 270.0
    },
    {
      "m": 2,
      "tmean": 24.47,
      "p": 332.4
    },
    {
      "m": 3,
      "tmean": 25.2,
      "p": 383.8
    },
    {
      "m": 4,
      "tmean": 24.65,
      "p": 46.2
    },
    {
      "m": 5,
      "tmean": 22.15,
      "p": 0.4
    },
    {
      "m": 6,
      "tmean": 21.05,
      "p": 0.0
    },
    {
      "m": 7,
      "tmean": 20.47,
      "p": 0.0
    },
    {
      "m": 8,
      "tmean": 22.05,
      "p": 0.0
    },
    {
      "m": 9,
      "tmean": 26.54,
      "p": 1.2
    },
    {
      "m": 10,
      "tmean": 25.64,
      "p": 0.2
    },
    {
      "m": 11,
      "tmean": 24.16,
      "p": 391.6
    },
    {
      "m": 12,
      "tmean": 24.5,
      "p": 314.6
    }
  ],
  "annual": {
    "tmin": 4.0,
    "tmean": 23.8,
    "tmax": 39.1,
    "p_total": 1740.4,
    "p_month_min": 0.0,
    "p_month_mean": 145.0,
    "p_month_max": 391.6,
    "coverage": 1.0
  }
}