{
  "station": "A207",
  "year": 2013,
  "months": [
    {
      "m": 1,
      "p": 157.6,
      "tmean": 26.4
    },
    {
      "m": 2,
      "p": 136.4,
      "tmean": 26.0
    },
    {
      "m": 3,
      "p": 264.2,
      "tmean": 26.2
    },
    {
      "m": 4,
      "p": 94.2,
      "tmean": 26.5
    },
    {
      "m": 5,
      "p": 74.6,
      "tmean": 26.4
    },
    {
      "m": 6,
      "p": 26.2,
      "tmean": 26.1
    },
    {
      "m": 7,
      "p": 2.4,
      "tmean": 26.9
    },
    {
      "m": 8,
      "p": 0.0,
      "tmean": 28.1
    },
    {
      "m": 9,
      "p": 0.8,
      "tmean": 29.5
    },
    {
      "m": 10,
      "p": 119.2,
      "tmean": 28.3
    },
    {
      "m": 11,
      "p": 125.4,
      "tmean": 26.4
    },
    {
      "m": 12,
      "p": 56.2,
      "tmean": 26.9
    }
  ],
  "annual": {
    "p_total": 1057.2,
    "p_month_mean": 88.1,
    "p_month_min": 0.0,
    "p_month_max": 264.2,
    "tmean": 27.0,
    "tmin": 26.0,
    "tmax": 29.5
  }
}