{
  "station": "A418",
  "year": 2015,
  "months": [
    {
      "m": 1,
      "p": 0.0,
      "tmean": 29.6
    },
    {
      "m": 2,
      "p": null,
      "tmean": 29.8
    },
    {
      "m": 3,
      "p": null,
      "tmean": 31.2
    },
    {
      "m": 4,
      "p": null,
      "tmean": 28.8
    },
    {
      "m": 5,
      "p": 0.4,
      "tmean": 25.9
    },
    {
      "m": 6,
      "p": 0.0,
      "tmean": 25.4
    },
    {
      "m": 7,
      "p": 0.0,
      "tmean": 25.7
    },
    {
      "m": 8,
      "p": 0.0,
      "tmean": 26.2
    },
    {
      "m": 9,
      "p": 0.0,
      "tmean": 29.9
    },
    {
      "m": 10,
      "p": 3.2,
      "tmean": 30.9
    },
    {
      "m": 11,
      "p": 86.6,
      "tmean": 30.1
    },
    {
      "m": 12,
      "p": 12.0,
      "tmean": 30.2
    }
  ],
  "annual": {
    "p_total": 102.2,
    "p_month_mean": 11.4,
    "p_month_min": 0.0,
    "p_month_max": 86.6,
    "tmean": 28.6,
    "tmin": 25.4,
    "tmax": 31.2
  }
}