{
  "station": "A039",
  "year": 2015,
  "months": [
    {
      "m": 1,
      "p": 9.6,
      "tmean": 26.1
    },
    {
      "m": 2,
      "p": null,
      "tmean": 25.9
    },
    {
      "m": 3,
      "p": 284.8,
      "tmean": 25.5
    },
    {
      "m": 4,
      "p": 160.4,
      "tmean": 25.9
    },
    {
      "m": 5,
      "p": 50.0,
      "tmean": 25.8
    },
    {
      "m": 6,
      "p": 0.0,
      "tmean": 25.8
    },
    {
      "m": 7,
      "p": 0.2,
      "tmean": 26.2
    },
    {
      "m": 8,
      "p": 0.0,
      "tmean": 27.6
    },
    {
      "m": 9,
      "p": 38.6,
      "tmean": 29.4
    },
    {
      "m": 10,
      "p": 44.6,
      "tmean": 29.7
    },
    {
      "m": 11,
      "p": 165.8,
      "tmean": 27.8
    },
    {
      "m": 12,
      "p": 3.8,
      "tmean": 29.4
    }
  ],
  "annual": {
    "p_total": 757.8,
    "p_month_mean": 68.9,
    "p_month_min": 0.0,
    "p_month_max": 284.8,
    "tmean": 27.1,
    "tmin": 25.5,
    "tmax": 29.7
  }
}