{
  "station": "A408",
  "year": 2008,
  "months": [
    {
      "m": 1,
      "p": 9.8,
      "tmean": 27.1
    },
    {
      "m": 2,
      "p": 179.2,
      "tmean": 26.8
    },
    {
      "m": 3,
      "p": 74.6,
      "tmean": 26.1
    },
    {
      "m": 4,
      "p": 19.6,
      "tmean": 26.5
    },
    {
      "m": 5,
      "p": 15.0,
      "tmean": 24.8
    },
    {
      "m": 6,
      "p": 50.6,
      "tmean": 22.6
    },
    {
      "m": 7,
      "p": 16.8,
      "tmean": 21.7
    },
    {
      "m": 8,
      "p": 14.2,
      "tmean": 23.2
    },
    {
      "m": 9,
      "p": 9.4,
      "tmean": 24.3
    },
    {
      "m": 10,
      "p": 3.6,
      "tmean": 25.4
    },
    {
      "m": 11,
      "p": 20.0,
      "tmean": 26.2
    },
    {
      "m": 12,
      "p": 174.4,
      "tmean": 25.7
    }
  ],
  "annual": {
    "p_total": 587.2,
    "p_month_mean": 48.9,
    "p_month_min": 3.6,
    "p_month_max": 179.2,
    "tmean": 25.0,
    "tmin": 21.7,
    "tmax": 27.1
  }
}