{
  "station": "A515",
  "year": 2009,
  "months": [
    {
      "m": 1,
      "p": 271.6,
      "tmean": 21.3
    },
    {
      "m": 2,
      "p": 222.8,
      "tmean": 22.1
    },
    {
      "m": 3,
      "p": 242.0,
      "tmean": 22.0
    },
    {
      "m": 4,
      "p": 60.6,
      "tmean": 19.6
    },
    {
      "m": 5,
      "p": 42.2,
      "tmean": 18.1
    },
    {
      "m": 6,
      "p": 42.6,
      "tmean": 15.3
    },
    {
      "m": 7,
      "p": 20.0,
      "tmean": 17.6
    },
    {
      "m": 8,
      "p": 39.4,
      "tmean": 18.1
    },
    {
      "m": 9,
      "p": 123.4,
      "tmean": 20.6
    },
    {
      "m": 10,
      "p": 164.4,
      "tmean": 21.0
    },
    {
      "m": 11,
      "p": 100.2,
      "tmean": 22.9
    },
    {
      "m": 12,
      "p": 17.2,
      "tmean": 21.5
    }
  ],
  "annual": {
    "p_total": 1346.4,
    "p_month_mean": 112.2,
    "p_month_min": 17.2,
    "p_month_max": 271.6,
    "tmean": 20.0,
    "tmin": 15.3,
    "tmax": 22.9
  }
}