{
  "station": "A352",
  "year": 2009,
  "months": [
    {
      "m": 1,
      "p": 148.8,
      "tmean": 25.8
    },
    {
      "m": 2,
      "p": 310.0,
      "tmean": 25.4
    },
    {
      "m": 3,
      "p": 185.8,
      "tmean": 25.9
    },
    {
      "m": 4,
      "p": 251.8,
      "tmean": 25.8
    },
    {
      "m": 5,
      "p": 344.2,
      "tmean": null
    },
    {
      "m": 6,
      "p": 259.4,
      "tmean": null
    },
    {
      "m": 7,
      "p": 294.8,
      "tmean": null
    },
    {
      "m": 8,
      "p": 201.2,
      "tmean": null
    },
    {
      "m": 9,
      "p": 75.8,
      "tmean": null
    },
    {
      "m": 10,
      "p": 9.2,
      "tmean": null
    },
    {
      "m": 11,
      "p": 15.4,
      "tmean": null
    },
    {
      "m": 12,
      "p": 20.6,
      "tmean": null
    }
  ],
  "annual": {
    "p_total": 2117.0,
    "p_month_mean": 176.4,
    "p_month_min": 9.2,
    "p_month_max": 344.2,
    "tmean": 25.7,
    "tmin": 25.4,
    "tmax": 25.9
  }
}