{
  "station": "A314",
  "year": 2017,
  "months": [
    {
      "m": 1,
      "p": 127.2,
      "tmean": 21.6
    },
    {
      "m": 2,
      "p": 164.4,
      "tmean": 21.4
    },
    {
      "m": 3,
      "p": 92.6,
      "tmean": 21.3
    },
    {
      "m": 4,
      "p": 211.2,
      "tmean": 21.4
    },
    {
      "m": 5,
      "p": 283.8,
      "tmean": 21.3
    },
    {
      "m": 6,
      "p": 138.2,
      "tmean": 20.9
    },
    {
      "m": 7,
      "p": 163.2,
      "tmean": 20.2
    },
    {
      "m": 8,
      "p": 35.6,
      "tmean": 20.8
    },
    {
      "m": 9,
      "p": 6.2,
      "tmean": 21.2
    },
    {
      "m": 10,
      "p": 60.4,
      "tmean": 21.6
    },
    {
      "m": 11,
      "p": 33.2,
      "tmean": 21.3
    },
    {
      "m": 12,
      "p": 66.0,
      "tmean": 21.8
    }
  ],
  "annual": {
    "p_total": 1382.0,
    "p_month_mean": 115.2,
    "p_month_min": 6.2,
    "p_month_max": 283.8,
    "tmean": 21.2,
    "tmin": 20.2,
    "tmax": 21.8
  }
}