{
  "station": "A747",
  "year": 2009,
  "months": [
    {
      "m": 1,
      "p": 238.6,
      "tmean": 23.7
    },
    {
      "m": 2,
      "p": 307.8,
      "tmean": 24.6
    },
    {
      "m": 3,
      "p": 371.6,
      "tmean": 24.3
    },
    {
      "m": 4,
      "p": 79.0,
      "tmean": 21.8
    },
    {
      "m": 5,
      "p": 38.0,
      "tmean": 20.2
    },
    {
      "m": 6,
      "p": 52.2,
      "tmean": 16.4
    },
    {
      "m": 7,
      "p": 28.6,
      "tmean": 19.3
    },
    {
      "m": 8,
      "p": 135.8,
      "tmean": 19.8
    },
    {
      "m": 9,
      "p": 127.4,
      "tmean": 22.5
    },
    {
      "m": 10,
      "p": 130.4,
      "tmean": 23.6
    },
    {
      "m": 11,
      "p": 247.0,
      "tmean": 25.4
    },
    {
      "m": 12,
      "p": 304.6,
      "tmean": 24.3
    }
  ],
  "annual": {
    "p_total": 2061.0,
    "p_month_mean": 171.8,
    "p_month_min": 28.6,
    "p_month_max": 371.6,
    "tmean": 22.2,
    "tmin": 16.4,
    "tmax": 25.4
  }
}