{
  "station": "A747",
  "year": 2015,
  "months": [
    {
      "m": 1,
      "p": 0.0,
      "tmean": 26.2
    },
    {
      "m": 2,
      "p": 69.2,
      "tmean": 24.3
    },
    {
      "m": 3,
      "p": 216.4,
      "tmean": 23.1
    },
    {
      "m": 4,
      "p": 28.2,
      "tmean": 22.8
    },
    {
      "m": 5,
      "p": 125.8,
      "tmean": 19.8
    },
    {
      "m": 6,
      "p": 6.0,
      "tmean": 19.4
    },
    {
      "m": 7,
      "p": 40.4,
      "tmean": 19.3
    },
    {
      "m": 8,
      "p": 4.6,
      "tmean": 20.4
    },
    {
      "m": 9,
      "p": 52.2,
      "tmean": 22.9
    },
    {
      "m": 10,
      "p": 59.6,
      "tmean": 25.6
    },
    {
      "m": 11,
      "p": 258.8,
      "tmean": 24.6
    },
    {
      "m": 12,
      "p": 233.4,
      "tmean": 24.8
    }
  ],
  "annual": {
    "p_total": 1094.6,
    "p_month_mean": 91.2,
    "p_month_min": 0.0,
    "p_month_max": 258.8,
    "tmean": 22.8,
    "tmin": 19.3,
    "tmax": 26.2
  }
}