{
  "station": "A439",
  "year": 2023,
  "months": [
    {
      "m": 1,
      "tmean": 26.03,
      "p": 51.4
    },
    {
      "m": 2,
      "tmean": 27.55,
      "p": 66.4
    },
    {
      "m": 3,
      "tmean": 26.83,
      "p": 56.6
    },
    {
      "m": 4,
      "tmean": 26.86,
      "p": 31.0
    },
    {
      "m": 5,
      "tmean": 26.83,
      "p": 2.6
    },
    {
      "m": 6,
      "tmean": 26.24,
      "p": 0.0
    },
    {
      "m": 7,
      "tmean": 26.13,
      "p": 0.0
    },
    {
      "m": 8,
      "tmean": 28.02,
      "p": 16.4
    },
    {
      "m": 9,
      "tmean": 30.13,
      "p": 0.6
    },
    {
      "m": 10,
      "tmean": 31.72,
      "p": 8.0
    },
    {
      "m": 11,
      "tmean": 30.1,
      "p": 103.6
    },
    {
      "m": 12,
      "tmean": 30.8,
      "p": 54.8
    }
  ],
  "annual": {
    "tmin": 13.2,
    "tmean": 28.1,
    "tmax": 41.3,
    "p_total": 391.4,
    "p_month_min": 0.0,
    "p_month_mean": 32.6,
    "p_month_max": 103.6,
    "coverage": 0.997
  }
}