{
  "station": "A703",
  "year": 2017,
  "months": [
    {
      "m": 1,
      "p": 156.8,
      "tmean": 24.7
    },
    {
      "m": 2,
      "p": 185.4,
      "tmean": 24.8
    },
    {
      "m": 3,
      "p": 216.6,
      "tmean": 24.1
    },
    {
      "m": 4,
      "p": 211.6,
      "tmean": 20.5
    },
    {
      "m": 5,
      "p": 153.8,
      "tmean": 20.2
    },
    {
      "m": 6,
      "p": 113.0,
      "tmean": 17.2
    },
    {
      "m": 7,
      "p": 6.0,
      "tmean": 17.4
    },
    {
      "m": 8,
      "p": 74.8,
      "tmean": 20.5
    },
    {
      "m": 9,
      "p": 23.4,
      "tmean": 24.0
    },
    {
      "m": 10,
      "p": 136.4,
      "tmean": 23.3
    },
    {
      "m": 11,
      "p": 187.6,
      "tmean": 23.8
    },
    {
      "m": 12,
      "p": 232.2,
      "tmean": 25.4
    }
  ],
  "annual": {
    "p_total": 1697.6,
    "p_month_mean": 141.5,
    "p_month_min": 6.0,
    "p_month_max": 232.2,
    "tmean": 22.2,
    "tmin": 17.2,
    "tmax": 25.4
  }
}